{
  "DataEntityMetadataJson": {
    "Tabla1": "{\"name\":\"Tabla1\",\"title\":\"Tabla1\",\"x-ms-permission\":\"read-write\",\"schema\":{\"type\":\"array\",\"items\":{\"type\":\"object\",\"properties\":{\"Id_lista\":{\"type\":\"string\",\"x-ms-keyOrder\":0,\"x-ms-keyType\":\"none\",\"x-ms-sort\":\"none\",\"title\":\"Id_lista\"},\"fuente\":{\"type\":\"string\",\"x-ms-keyOrder\":0,\"x-ms-keyType\":\"none\",\"x-ms-sort\":\"none\",\"title\":\"fuente\"},\"nombre\":{\"type\":\"string\",\"x-ms-keyOrder\":0,\"x-ms-keyType\":\"none\",\"x-ms-sort\":\"none\",\"title\":\"nombre\"},\"interprete\":{\"type\":\"string\",\"x-ms-keyOrder\":0,\"x-ms-keyType\":\"none\",\"x-ms-sort\":\"none\",\"title\":\"interprete\"},\"genero\":{\"type\":\"string\",\"x-ms-keyOrder\":0,\"x-ms-keyType\":\"none\",\"x-ms-sort\":\"none\",\"title\":\"genero\"},\"foto\":{\"type\":\"string\",\"x-ms-keyOrder\":0,\"x-ms-keyType\":\"none\",\"x-ms-sort\":\"none\",\"title\":\"foto\"},\"momento\":{\"type\":\"string\",\"x-ms-keyOrder\":0,\"x-ms-keyType\":\"none\",\"x-ms-sort\":\"none\",\"title\":\"momento\"},\"relato\":{\"type\":\"string\",\"x-ms-keyOrder\":0,\"x-ms-keyType\":\"none\",\"x-ms-sort\":\"none\",\"title\":\"relato\"},\"Columna1\":{\"type\":\"string\",\"x-ms-keyOrder\":0,\"x-ms-keyType\":\"none\",\"x-ms-sort\":\"none\",\"title\":\"Columna1\"},\"__PowerAppsId__\":{\"type\":\"string\",\"x-ms-keyOrder\":1,\"x-ms-keyType\":\"primary\",\"x-ms-sort\":\"none\",\"x-ms-permission\":\"read-only\",\"title\":\"Row id\"}}}}}"
  },
  "EntityName": "Tabla1",
  "TableName": "Tabla1"
}